agent_desk/__init__.py
agent_desk/tool.py
agent_desk/util.py
agent_desk/vm/kubernetes.py
agent_desk/vm/local.py
agent_desk-0.1.8.dist-info/LICENSE
agent_desk-0.1.8.dist-info/METADATA
agent_desk-0.1.8.dist-info/WHEEL
agent_desk-0.1.8.dist-info/RECORD
